<?xml version="1.0"?>


<!-- This file was originally part of the book     -->
<!--   Modeling, Functions, and Graphs   -->
<!--           4th                                     -->
<!-- Copyright (C) Katherine Yoshiwara      -->

<exercises xml:id="section-7-1-exercises"  xmlns:xi="http://www.w3.org/2001/XInclude">
    <title>Homework</title>

<exercisegroup cols="2"><introduction><p>Multiply.</p></introduction>

<exercise number="1"><statement><p><m>(3x - 2)(4x^2 + x - 2)</m></p></statement>
<answer><p><m>12x^3 - 5x^2 - 8x + 4</m></p></answer>
</exercise>

<exercise number="2"><statement><p><m>(2x + 3)(3x^2 - 4x + 2)</m></p></statement>
</exercise>

<exercise number="3"><statement><p><m>(x - 2)(x - 1)(x - 3)</m></p></statement>
<answer><p><m>x^3 - 6x^2 + 11x - 6</m></p></answer>
</exercise>

<exercise number="4"><statement><p><m>(z - 5)(z + 6)(z - 1)</m></p></statement>
</exercise>

<exercise number="5"><statement><p><m>(2a^2 - 3a + 1)(3a^2 + 2a - 1)</m></p></statement>
<answer><p><m>6a^4 - 5a^3 - 5a^2 + 5a - 1</m></p></answer>
</exercise>

<exercise number="6"><statement><p><m>(b^2 - 3b + 5)(2b^2 - b + 1)</m></p></statement>
</exercise>

<exercise number="7"><statement><p><m>(y - 2)(y + 2)(y + 4)(y + 1)</m></p></statement>
<answer><p><m>y^4 + 5y^3 - 20y - 16</m></p></answer>
</exercise>

<exercise number="8"><statement><p><m>(z + 3)(z + 2)(z - 1)(z + 1)</m></p></statement>
</exercise>
</exercisegroup>


<exercisegroup ><introduction><p>Find the first three terms of the product in ascending powers. (Do not compute the entire product!)</p></introduction>

<exercise number="9"><statement><p><m>(2 - x + 3x^2)(3 + 2x - x^2 + 2x^4)</m></p></statement>
<answer><p><m>6 + x + 5x^2</m></p></answer>
</exercise>

<exercise number="10"><statement><p><m>(1 + x - 2x^2)(-3 + 2x - 4x^3)</m></p></statement>
</exercise>

<exercise number="11"><statement><p><m>(1 - 2x^2 - x^4)(4 + x^2 - 2x^4)</m></p></statement>
<answer><p><m>4 - 7x^2 - 8x^4</m></p></answer>
</exercise>

<exercise number="12"><statement><p><m>(3 + 2x)(5 - 2x^2 - 3x^3 - x^5 + 2x^6)</m></p></statement>
</exercise>
</exercisegroup>


<exercisegroup ><introduction><p>Find the indicated term in each product. (Do not compute the entire product!)</p></introduction>

<exercise number="13"><statement><p><m>(4 + 2x - x^2)(2 - 3x + 2x^2)</m>; <m>x^2</m></p></statement>
<answer><p><m>0x^2</m></p></answer>
</exercise>

<exercise number="14"><statement><p><m>(1 - 2x + 3x^2)(6 - x - x^3)</m>; <m>x^3</m></p></statement>
</exercise>

<exercise number="15"><statement><p><m>(3x + x^3 - 7x^5)(1 + 4x - 3x^2)</m>; <m>x^3</m></p></statement>
<answer><p><m>-8x^3</m></p></answer>
</exercise>

<exercise number="16"><statement><p><m>(2 + 3x^2 + 2x^4)(2 - x - x^2 - x^4)</m>; <m>x^4</m></p></statement>
</exercise>
</exercisegroup>


<exercisegroup ><introduction><p>Without performing the multiplication, give the degree of each product.</p></introduction>

<exercise number="17"><statement><p><ol>
    <li><p><m>(x^2 - 4) (3x^2 - 6x + 2)</m></p></li>
    <li><p><m>(x - 3) (2x - 5) (x^3 - x + 2)</m></p></li>
    <li><p><m>(3x^2 + 2x) (x^3 + 1) (-2x^2 + 8)</m></p></li>
</ol></p></statement>
<answer><p><ol cols="3">
    <li><p><m>4</m></p></li>
    <li><p><m>5</m></p></li>
    <li><p><m>7</m></p></li>
</ol></p></answer>
</exercise>

<exercise number="18"><statement><p><ol>
    <li><p><m>(6x^2 - 1) (4x^2 - 9)</m></p></li>
    <li><p><m>(3x + 4) (3x + 1) (2x^3 + x^2 - 7)</m></p></li>
    <li><p><m>(x^2 - 3) (2x^3 - 5x^2 + 2) (-x^3 - 5x)</m></p></li>
</ol></p></statement>
</exercise>
</exercisegroup>


<exercisegroup ><introduction><p>Verify the following products discussed in the text.</p></introduction>

<exercise number="19"><statement><p><m>(x + y)^3 = x^3 + 3x^2 y + 3xy^2 + y^3</m></p></statement>
<answer><p><m>
    \begin{aligned}
    (x + y)^3 \amp = (x + y)(x + y)^2\\
    \amp = (x + y)(x^2 + 2xy + y^2) \\
    \amp = x^3 + 2x^2 y + xy^2 + x^2 y + 2xy^2 + y^3\\
    \amp = x^3 + 3x^2 y + 3xy^2 + y^3
    \end{aligned}
</m></p></answer>
</exercise>

<exercise number="20"><statement><p><m>(x - y)^3 = x^3 - 3x^2 y + 3xy^2 - y^3</m></p></statement></exercise>

<exercise number="21"><statement><p><m>(x + y)(x^2 - xy + y^2) = x^3 + y^3</m></p></statement>
<answer><p><m>
    \begin{aligned}
    (x + y)(x^2 - xy + y^2) 
    \amp = x^3 -x^2 y + xy^2 + x^2 y -xy^2 + y^3\\
    \amp = x^3 + y^3
    \end{aligned}
</m></p></answer>
</exercise>

<exercise number="22"><statement><p><m>(x - y)(x^2 + xy + y^2) = x^3 - y^3</m></p></statement></exercise>
</exercisegroup>


<exercise number="23"><statement><p><ol>
    <li><p>As if you were addressing a classmate, explain how to remember the formula for expanding <m>(x + y)^3</m>. In particular, mention the exponents on each term and the numerical coefficients.</p></li>
    <li><p>Explain how to remember the formula for expanding <m>(x - y)^3</m>, assuming your listener already knows the formula for <m>(x + y)^3</m>.</p></li>
</ol></p></statement>
<answer><p><ol>
    <li><p>The formula begins with <m>x^3</m> and ends with <m>y^3</m>. As you proceed from term to term, the exponents on <m>x</m> decrease while the exponents on <m>y</m> increase, and on each term the sum of the exponents is <m>3</m>. The coefficients of the two middle terms are both <m>3</m>.</p></li>
    <li><p>The formula is the same as for <m>(x - y)3</m>, except that the terms alternate in sign.</p></li>
</ol></p></answer>
</exercise>

<exercise number="24"><statement><p><ol>
    <li><p>As if you were addressing a classmate, explain how to remember the formula for factoring a sum of two cubes. Pay particular attention to the placement of the variables and the signs of the terms.</p></li>
    <li><p>Explain how to remember the formula for factoring a difference of two cubes, assuming your listener already knows how to factor a sum of two cubes.</p></li>
</ol></p></statement>
</exercise>


<exercisegroup cols="4"><introduction><p>Use the formulas for the cube of a binomial to expand the products.</p></introduction>

<exercise number="25"><statement><p><m>(1 + 2z)^3</m></p></statement>
<answer><p><m>1+6z+12z^2+8z^3</m></p></answer>
</exercise>


<exercise number="26"><statement><p><m>(1 - x^2)^3</m></p></statement>
</exercise>

<exercise number="27"><statement><p><m>(1 -5\sqrt{t})^3</m></p></statement>
<answer><p><m>1-15\sqrt{t}+75t-125t\sqrt{t} </m></p></answer>
</exercise>


<exercise number="26"><statement><p><m>\left(1 - \dfrac{3}{a}\right)^3</m></p></statement>
</exercise>
</exercisegroup>


<exercisegroup cols="2"><introduction><p>Write each product as a polynomial and simplify.</p></introduction>

<exercise number="29"><statement><p><m>(x - 1) (x^2 + x + 1)</m></p></statement>
<answer><p><m>x^3-1</m></p></answer>
</exercise>

<exercise number="30"><statement><p><m>(x +2) (x^2 -2 x + 4)</m></p></statement>
</exercise>

<exercise number="31"><statement><p><m>(2x + 1)(4x^2 - 2x + 1)</m></p></statement>
<answer><p><m>8x^3+1</m></p></answer>
</exercise>

<exercise number="32"><statement><p><m>(3x - 1)(9x^2 + 3x + 1)</m></p></statement>
</exercise>

<exercise number="33"><statement><p><m>(3a - 2b)(9a^2 + 6ab + 4b^2)</m></p></statement>
<answer><p><m>27a^3 - 8b^3</m></p></answer>
</exercise>

<exercise number="34"><statement><p><m>(2a + 3b)(4a^2 - 6ab + 9b^2)</m></p></statement>
</exercise>
</exercisegroup>


<exercisegroup cols="3"><introduction><p>Factor completely.</p></introduction>

<exercise number="35"><statement><p><m>x^3 + 27</m></p></statement>
<answer><p><m>(x+3)(x^2-3x+9) </m></p></answer>
</exercise>

<exercise number="36"><statement><p><m>y^3 -1</m></p></statement>
</exercise>

<exercise number="37"><statement><p><m>a^3 -8 b^3</m></p></statement>
<answer><p><m>(a-2b)(a^2+2ab+4b^2) </m></p></answer>
</exercise>

<exercise number="38"><statement><p><m>27a^3 +b^3</m></p></statement></exercise>

<exercise number="39"><statement><p><m>x^3y^6 -1</m></p></statement>
<answer><p><m>(xy^2-1)(x^2y^4+xy^2+1) </m></p></answer>
</exercise>

<exercise number="40"><statement><p><m>8 + x^{12}y^3</m></p></statement></exercise>

<exercise number="41"><statement><p><m>27a^3 + 64b^3</m></p></statement>
<answer><p><m>(3a+4b)(9a^2 -12ab+16b^2) </m></p></answer>
</exercise>

<exercise number="42"><statement><p><m>8a^3 - 125t^9</m></p></statement></exercise>

<exercise number="43"><statement><p><m>125a^3b^3 - 1</m></p></statement>
<answer><p><m>(5ab-1)(25a^2b^2+5ab+1) </m></p></answer>
</exercise>

<exercise number="44"><statement><p><m>64a^3b^3 + 1</m></p></statement></exercise>

<exercise number="45"><statement><p><m>64t^9 + w^6</m></p></statement>
<answer><p><m>(4t^3+w^2)(16t^6 -4t^3w^2+w^4) </m></p></answer>
</exercise>

<exercise number="46"><statement><p><m>w^{15} - 125t^9</m></p></statement></exercise>
</exercisegroup>


<exercise number="47"><statement><p>
    <sidebyside widths="50% 20%">
    <ol>
    <li><p>Write a polynomial function, <m>A(x)</m>, that gives the area of the front face of the speaker frame (the region in color) in the figure.</p>
    </li>
    <li><p>If <m>x=8</m> inches, find the area of the front face of the frame.</p></li>
</ol>
<p><image source="images/fig-7-1-47"><description>speaker frame</description></image></p></sidebyside>
</p> </statement>
<answer><p><ol cols="2">
    <li><p><m>\left(6-\dfrac{5}{4}\pi \right)x^2 </m></p></li>
    <li><p><m>\approx 132.67</m> square inches</p></li>
</ol></p></answer>
</exercise>

<exercise number="48"><statement><p>
    <sidebyside widths="50% 20%">
        <ol>
    <li><p>A Norman window is shaped like a rectangle whose length is twice its width, with a semicircle at the top (see the figure). Write a polynomial, <m>A(x)</m>, that gives its area.</p></li>
    <li><p>If <m>x=3</m> feet, find the area of the front face of the frame.</p></li>
</ol>
<p><image source="images/fig-7-1-48"><description>Norman window</description></image></p> </sidebyside>
</p></statement>
</exercise>

<exercise number="49"><statement><p>
    <sidebyside widths="50% 20%">
        <ol>
    <li><p>A grain silo is built in the shape of a cylinder with a hemisphere on top (see the figure). Write an expression for the volume of the silo in terms of the radius and height of the cylindrical portion of the silo.</p></li>
    <li><p>If the total height of the silo is five times its radius, write a polynomial function <m>V(r )</m> in one variable for its volume.</p></li>
</ol>
<p><image source="images/fig-7-1-49"><description>grain silo</description></image></p> </sidebyside></p></statement>
<answer><p><ol>
    <li><p><m>\dfrac{2}{3}\pi r^3+\pi r^2h </m></p></li>
    <li><p><m>V(r)=\dfrac{14}{3}\pi r^3 </m></p></li>
</ol></p></answer>
</exercise>

<exercise number="50"><statement><p><ol>
    <li><sidebyside widths="70% 20%"><p>A cold medication capsule is shaped like a cylinder with a hemispherical cap on each end (see the figure). Write an expression for the volume of the capsule in terms of the radius and length of the cylindrical portion.</p>
    <p><image source="images/fig-7-1-50"><description>capsule</description></image></p> </sidebyside>
    </li>
    <li><p>If the radius of the capsule is one-fourth of its overall length, write a polynomial function <m>V(r )</m> in one variable for its volume.</p></li>
</ol></p></statement></exercise>

<exercise number="51"><statement><p>Jack invests <m>\$500</m> in an account bearing interest rate <m>r</m>, compounded annually. This means that each year his account balance is increased by a factor of <m>1 + r</m>.<ol>
    <li><p>Write expressions for the amount of money in Jack's account after <m>2</m> years, after <m>3</m> years, and after <m>4</m> years.</p></li>
    <li><p>How much money will be in Jack's account at the end of <m>2</m> years, <m>3</m> years, and <m>4</m> years if the interest rate is <m>8\%</m>?</p></li>
</ol></p></statement>
<answer><p><ol>
    <li><p><m>500(1 + r )^2</m>; <m>500(1 + r )^3</m>; <m>500(1 + r )^4 </m></p></li>
    <li><p><m>500r^2 + 1000r + 500</m>; <m>500r^3 + 1500r^2 + 1500r + 500</m>; <m>500r^4 + 2000r^3 + 3000r^2 + 2000r + 500 </m></p></li>
</ol></p></answer>
</exercise>

<exercise number="52"><statement><p>A small company borrows $800 for start-up costs and agrees to repay the loan at interest rate r, compounded
annually. This means that each year the debt is increased by a factor of <m>1 + r</m>.<ol>
    <li><p>Write expressions for the amount of money the company will owe if it repays the loan after <m>2</m> years, after <m>3</m> years, or after <m>4</m> years.</p></li>
    <li><p>Expand the expressions you found in part (a) as polynomials.</p></li>
    <li><p>How much money will the company owe after <m>2</m> years, after <m>3</m> years, or after <m>4</m> years at an interest rate of <m>12\%</m>?</p></li>
</ol></p></statement></exercise>


<exercise number="53"><statement><p>A paper company plans to make boxes without tops from sheets of cardboard <m>12</m> inches wide and <m>16</m> inches long. The company will cut out four squares of side <m>x</m> inches from the corners of the sheet and fold up the edges as shown in the figure. 
<image source="images/fig-7-1-53"  width="50%">
  <description>
    box
  </description>
</image> 
<ol>
    <li><p>Write expressions in terms of <m>x</m> for the length, width, and height of the resulting box.</p></li>
    <li><p>Write a formula for the volume, <m>V</m>, of the box as a function of <m>x</m>.</p></li>
    <li><p>What is the domain of the function <m>V</m>? (What are the largest and smallest reasonable values for <m>x</m>?)</p></li>
    <li><p>Make a table of values for <m>V(x) </m> on its domain.</p></li>
    <li><p>Graph your function <m>V</m> in a suitable window.</p></li>
    <li><p>Use your graph to find the value of <m>x</m> that will yield a box with maximum possible volume. What is the maximum possible volume?</p></li>
</ol></p></statement>
<answer><p><ol>
    <li><p>Length: <m>16 - 2x</m>; Width: <m>12 - 2x</m>; Height: <m>x</m></p></li>
    <li><p><m>V = x(16 - 2x)(12 - 2x)</m></p></li>
    <li><p>Real numbers between <m>0</m> and <m>6</m></p></li>
    <li><p><sidebyside><tabular left="minor" right="minor" top="minor" bottom="minor" halign="center">
        <row>
            <cell><m>x</m></cell>
            <cell><m>1</m></cell>
            <cell><m>2</m></cell>
            <cell><m>3</m></cell>
            <cell><m>4</m></cell>
            <cell><m>5</m></cell>
        </row>
        <row>
            <cell><m>V</m></cell>
            <cell><m>140</m></cell>
            <cell><m>192</m></cell>
            <cell><m>180</m></cell>
            <cell><m>128</m></cell>
            <cell><m>60</m></cell>
        </row>
    </tabular></sidebyside></p></li>
    <li><p><image source="images/fig-ans-7-1-53.jpg"  width="35%"><description>cubic</description></image> </p></li>
    <li><p><m>2.26</m> in, <m>194.07</m> cu in</p></li>
</ol></p></answer>
</exercise>

<exercise number="54"><statement><p>The paper company also plans to make boxes with tops from <m>12</m>-inch by <m>16</m>-inch sheets of cardboard by cutting out the shaded areas shown in the figure and folding
along the dotted lines.
<image source="images/fig-7-1-54"  width="50%">
  <description>
    box
  </description>
</image> 
<ol>
    <li><p>Write expressions in terms of <m>x</m> for the length, width, and height of the resulting box.</p></li>
    <li><p>Write a formula for the volume, <m>V</m>, of the box as a function of <m>x</m>.</p></li>
    <li><p>What is the domain of the function <m>V</m>? (What are the largest and smallest reasonable values for <m>x</m>?)</p></li>
    <li><p>Make a table of values for <m>V(x) </m> on its domain.</p></li>
    <li><p>Graph your function <m>V</m> in a suitable window.</p></li>
    <li><p>Use your graph to find the value of <m>x</m> that will yield a box with maximum possible volume. What is the maximum possible volume?</p></li>
</ol></p></statement></exercise>


<exercisegroup><introduction><p>Use your graphing calculator to help you answer the questions in Problems 55<ndash/>62. Then verify your answers algebraically.</p></introduction>

<exercise number="55"><statement><p>
    A doctor who is treating a heart patient wants to prescribe medication to lower the patient's blood pressure. The body's reaction to this medication is a function of the dose administered. If the patient takes <m>x</m> milliliters of the medication, his blood pressure should decrease by <m>R = f (x)</m> points, where
    <me>f (x) = 3x^2 - \dfrac{1}{3}x^3 </me>
    <ol>
        <li><p>For what values of <m>x</m> is <m>R = 0</m>?</p></li>
        <li><p>Find a suitable domain for the function and explain why you chose this domain.</p></li>
        <li><p>Graph the function <m>f</m> on its domain.</p></li>
        <li><p>How much should the patient's blood pressure drop if he takes <m>2</m> milliliters of medication?</p></li>
        <li><p>What is the maximum drop in blood pressure that can be achieved with this medication?</p></li>
        <li><p>There may be risks associated with a large change in blood pressure. How many milliliters of the medication should be administered to produce half the maximum possible drop in blood pressure?</p></li>
    </ol></p></statement>
<answer><p><ol >
    <li><p><m>0, 9</m></p></li>
    <li><p><m>0\le x \le 9</m>; <m>R\ge 0</m> for these values</p></li>
    <li><p><image source="images/fig-ans-7-1-55.jpg"  width="35%"><description>cubic</description></image> </p></li>
    <li><p><m>\dfrac{28}{3} </m> points</p></li>
    <li><p><m>36</m> points</p></li>
    <li><p><m>3</m> ml or <m>8.2</m> ml; But, if <m>3</m> ml work, then there is no need to use <m>8.2</m> ml of this medication</p></li>
</ol></p></answer>
</exercise>

<exercise number="56"><statement><p>A soup bowl has the shape of a hemisphere of radius <m>6</m> centimeters. The volume of the soup in the bowl, <m>V = f (x)</m>, is a function of the depth, <m>x</m>, of the soup.
<image source="images/fig-7-1-56"  width="25%">
  <description>
    soup bowl
  </description>
</image>
<ol>
    <li><p>What is the domain of <m>f</m>? Why?</p></li>
    <li><p>The function <m>f</m> is given by
    <me>f (x) = 6 \pi x^2 -\frac{\pi}{3}x^3 </me>
    Graph the function on its domain.</p></li>
    <li><p>What is the volume of the soup if it is <m>3</m> centimeters deep?</p></li>
    <li><p>What is the maximum volume of soup that the bowl can hold?</p></li>
    <li><p>Find the depth of the soup (to within <m>2</m> decimal places of accuracy) when the bowl is filled to half its capacity.</p></li>
</ol> </p></statement></exercise>

<exercise number="57"><statement><p>The population, <m>P(t) </m>, of Cyberville has been growing according to the formula
<me>P(t) = t^3 - 63t^2 + 1403t + 900</me>
where <m>t</m> is the number of years since 1970.
<ol>
    <li><p>Graph <m>P(t)</m> in the window
         <md>
            <mrow>
                \small{\text{Xmin}} \amp = 0 \amp\amp \small{\text{Xmax}} = 47
            </mrow>
            <mrow>
                \small{\text{Ymin}} \amp = 0 \amp\amp \small{\text{Ymax}} = 20,000
            </mrow>
        </md>
    </p></li>
    <li><p>What was the population in 1970? In 1985? In 2004?</p></li> 
    <li><p>By how much did the population grow from 1970 to 1971? From 1985 to 1986? From 2004 to 2005?</p></li> 
    <li><p>Approximately when was the population growing at the slowest rate, that is, when is the graph the least steep?</p></li>
</ol></p></statement>
<answer><p><ol cols="2">
    <li><p><image source="images/fig-ans-7-1-57.jpg"  width="80%"><description>cubic</description></image> </p></li>
    <li><p><m>900</m>; <m>11,145</m>; <m>15,078</m></p></li>
    <li><p><m>1341</m>; <m>171</m>; <m>627</m></p></li>
    <li><p>Between 1990 and 1991</p></li>
</ol></p></answer>
</exercise>

<exercise number="58"><statement><p>The annual profit, <m>P(t)</m>, of the Enviro Company, in thousands of dollars, is given by
<me>P(t) = 2t^3 - 152t^2 + 3400t + 30</me>
where <m>t</m> is the number of years since 1960, the first year
that the company showed a profit.
<ol>
    <li><p>Graph <m>P(t)</m> in the window
         <md>
            <mrow>
                \small{\text{Xmin}} \amp = 0 \amp\amp \small{\text{Xmax}} = 94
            </mrow>
            <mrow>
                \small{\text{Ymin}} \amp = 0 \amp\amp \small{\text{Ymax}} = 50,000
            </mrow>
        </md>
    </p></li>
    <li><p>What was the profit in 1960? In 1980? In 2000?</p></li>
    <li><p>How did the profit change from 1960 to 1961? From 1980 to 1981? From 2000 to 2001?</p></li>
    <li><p>During which years did the profit decrease from one year to the next?</p></li>
</ol></p></statement></exercise>

<exercise number="59"><statement><p>The total annual cost of educating postgraduate research students at an Australian university, in thousands of dollars, is given by the function
<me>C(x) = 0.0173x^3 - 0.647x^2 + 9.587x + 195.366</me>
where <m>x</m> is the number of students, in hundreds. (Source: Creedy, Johnson, and Valenzuela, 2002)
<ol>
    <li><p>Graph the function in a suitable window for up to <m>3500</m> students.</p></li>
    <li><p>Describe the concavity of the graph. For what value of <m>x</m> is the cost growing at the slowest rate?</p></li>
    <li><p>Approximately how many students can be educated for <m>\$350,000</m>?</p></li>
</ol></p></statement>
<answer><p><ol>
    <li><p><image source="images/fig-ans-7-1-59.jpg"  width="40%"><description>cubic</description></image> </p></li>
    <li><p>The graph is concave down until about <m>x = 12.5</m> and is concave up afterwards. The cost is growing at the slowest rate at the inflection point at about <m>x = 12.5</m>, or <m>1250</m> students.</p></li>
    <li><p>About <m>2738</m></p></li>
</ol></p></answer>
</exercise>

<exercise number="60"><statement><p>It has been proposed that certain cubic functions model the response of wheat and barley to nitrogen fertilizer. These functions exhibit a "plateau" that fits observations
better than the standard quadratic model. (See <xref ref="exercise-quadratic-nitrogen-fertilizer" text="global">Problem</xref> of <xref ref="Curve-Fitting" text="type-global"/>.) In trials in Denmark, the yield per acre was a function of the amount of nitrogen applied. A typical response function is
<me>Y(x) = 54.45 + 0.305x - 0.001655x^2 + 2.935 \times 10^{-6}x^3</me>
where <m>x</m> is the amount of fertilizer, in kilograms per acre.
(Source: Beattie, Mortensen, and Knudsen, 2005)
<ol>
    <li><p>Graph the function on the domain <m>[0, 400]</m>.</p></li>
    <li><p>Describe the concavity of the graph. In reality, the yield does not increase after reaching its plateau. Give a suitable domain for the model in this application.</p></li>
    <li><p>Estimate the maximum yield attainable and the optimum application of fertilizer.</p></li>
</ol></p></statement></exercise>

<exercise number="61"><statement><p>During an earthquake, Nordhoff Street split in two, and one section shifted up several centimeters. Engineers
created a ramp from the lower section to the upper section. In the coordinate system shown in the figure below, the ramp is part of the graph of 
<me>y = f (x) = -0.00004x^3 - 0.006x^2 + 20</me></p>
<p><image source="images/fig-7-1-61"  width="50%"><description>ramp</description></image></p> 
<p></p>
<ol>
    <li><p>By how much did the upper section of the street shift
during the earthquake?</p></li>
<li><p>What is the horizontal distance from the bottom of the ramp to the raised part of the street?</p></li>
</ol></statement>
<answer><p><ol cols="2">
    <li><p><m>20</m> cm</p></li>
    <li><p><m>100</m> cm</p></li>
</ol></p></answer>
</exercise>

<exercise number="62"><statement><p>The off-ramp from a highway connects to a parallel one-way road. The accompanying figure shows the highway,
the off-ramp, and the road. The road lies on the <m>x</m>-axis, and the off-ramp begins at a point on the <m>y</m>-axis. The offramp
is part of the graph of the polynomial <me>y = f (x) = 0.00006x^3 - 0.009x^2 + 30</me></p>
<p><image source="images/fig-7-1-62"  width="55%"><description>off-ramp</description></image></p> 
<p></p>
<ol>
    <li><p>How far east of the exit does the off-ramp meet the one-way road?</p></li>
    <li><p>How far apart are the highway and the road?</p></li>
</ol>
</statement></exercise>
</exercisegroup>


<exercise number="63"><statement><p>The number of minutes of daylight per day in Chicago is approximated by the polynomial <me>H(t) = 0.000\, 000\, 525t^4 - 0.0213t^2 + 864</me> where <m>t</m> is the number of days since the summer solstice. The approximation is valid for <m>-74 \lt t \lt 74</m>. (A negative value of <m>t</m> corresponds to a number of days before the summer solstice.)
<ol>
    <li><p>Use a table of values with increments of <m>10</m> days to estimate the range of the function on its domain.</p></li>
    <li><p>Graph the polynomial on its domain.</p></li>
    <li><p>How many minutes of daylight are there on the summer solstice?</p></li>
    <li><p>How much daylight is there two weeks before the solstice?</p></li>
    <li><p>When are the days more than <m>14</m> hours long?</p></li>
    <li><p>When are the days less than <m>13</m> hours long?</p></li>
</ol></p></statement>
<answer><p><ol>
    <li><p><m>763.10 \lt H(t) \lt 864</m></p></li>
    <li><p><image source="images/fig-ans-7-1-63.jpg"  width="40%"><description>quartic</description></image> </p></li>
    <li><p><m>864</m> min</p></li>
    <li><p><m>859.8</m> min</p></li>
    <li><p>Within <m>34</m> days of the summer solstice</p></li>
    <li><p>More than <m>66</m> days from the summer solstice</p></li>
</ol></p></answer>
</exercise>

<exercise number="64"><statement><p>The water level (in feet) at a harbor is approximated by the polynomial <me>W(t) = 0.00733t^4 - 0.332t^2 + 9.1</me> where <m>t</m> is the number of hours since the high tide. The
approximation is valid for <m>-4 \le t \le 4</m>. (A negative value of <m>t</m> corresponds to a number of hours before the high tide.)
<ol>
    <li><p>Use a table of values to estimate the range of the function on its domain.</p></li>
    <li><p>Graph the polynomial on its domain.</p></li>
    <li><p>What is the water level at high tide?</p></li>
    <li><p>What is the water level <m>3</m> hours before high tide?</p></li>
    <li><p>When is the water level below <m>8</m> feet?</p></li>
    <li><p>When is the water level above <m>7</m> feet?</p></li>
</ol></p></statement></exercise>

</exercises>